boss/__init__.py
boss/boss.py
boss/configuration.py
boss/container.py
boss/dummies.py
boss/factory.py
boss/helper.py
boss/multiprocess.py
boss/starter.py
boss/worker.py
heros_boss-0.6.3.dist-info/METADATA
heros_boss-0.6.3.dist-info/WHEEL
heros_boss-0.6.3.dist-info/licenses/LICENSE
heros_boss-0.6.3.dist-info/RECORD
