Metadata-Version: 2.4
Name: heros-boss
Version: 0.6.3
Summary: Configuration driven object/HERO starter
Project-URL: Homepage, https://gitlab.com/atomiq-project/boss
Project-URL: Repository, https://gitlab.com/atomiq-project/boss
Project-URL: Bug Tracker, https://gitlab.com/atomiq-project/boss/issues
Author-email: Thomas Niederprüm <t.niederpruem@rptu.de>, Suthep Pomjaksilp <s.pomjaksilp@rptu.de>, Christian Hölzl <choelzl@pi5.physik.uni-stuttgart.de>
Maintainer-email: Thomas Niederprüm <t.niederpruem@rptu.de>, Suthep Pomjaksilp <s.pomjaksilp@rptu.de>, Christian Hölzl <choelzl@pi5.physik.uni-stuttgart.de>
License-File: LICENSE
Keywords: pub/sub,remote object,rpc,zenoh
Classifier: Development Status :: 4 - Beta
Classifier: Environment :: Console
Classifier: Intended Audience :: Developers
Classifier: Intended Audience :: Science/Research
Classifier: Programming Language :: Python :: 3
Classifier: Programming Language :: Python :: 3 :: Only
Classifier: Topic :: Communications
Requires-Python: >=3.10
Requires-Dist: heros>=0.8
Provides-Extra: dev
Requires-Dist: hatch; extra == 'dev'
Requires-Dist: pip; extra == 'dev'
Requires-Dist: pre-commit>=4; extra == 'dev'
Requires-Dist: pytest-cov>=4.0; extra == 'dev'
Requires-Dist: pytest>=8; extra == 'dev'
Requires-Dist: ruff>=0.12; extra == 'dev'
Provides-Extra: docs
Requires-Dist: furo>=2024; extra == 'docs'
Requires-Dist: hatch; extra == 'docs'
Requires-Dist: sphinx-argparse; extra == 'docs'
Requires-Dist: sphinx-autoapi>=3; extra == 'docs'
Requires-Dist: sphinx-autodoc-typehints>=3; (python_version >= '3.11') and extra == 'docs'
Requires-Dist: sphinx-copybutton; extra == 'docs'
Requires-Dist: sphinx-tabs; extra == 'docs'
Requires-Dist: sphinx>=8; (python_version >= '3.11') and extra == 'docs'
Requires-Dist: toml; extra == 'docs'
